base26/__init__.py
base26/__main__.py
base26/base26.py
base26-1.0.5.dist-info/LICENSE.txt
base26-1.0.5.dist-info/METADATA
base26-1.0.5.dist-info/WHEEL
base26-1.0.5.dist-info/top_level.txt
base26-1.0.5.dist-info/RECORD
