Metadata-Version: 2.1
Name: base26
Version: 1.0.5
Summary: Package implements base26 encoding/decoding algorithm.
Author-email: Sergey Popinveskiy <sergey@yggdr.io>
License: MIT
Project-URL: Source, https://github.com/yggdr-corp/pybase26
Classifier: Development Status :: 4 - Beta
Classifier: Environment :: Console
Classifier: Intended Audience :: Developers
Classifier: License :: OSI Approved :: MIT License
Classifier: Topic :: Software Development :: Libraries
Classifier: Topic :: Utilities
Classifier: Programming Language :: Python
Classifier: Programming Language :: Python :: 3 :: Only
Classifier: Programming Language :: Python :: 3
Classifier: Programming Language :: Python :: 3.8
Classifier: Programming Language :: Python :: 3.9
Classifier: Programming Language :: Python :: 3.10
Classifier: Topic :: Software Development :: Libraries
Classifier: Topic :: Utilities
Requires-Python: >=3.8
License-File: LICENSE.txt
Provides-Extra: dev
Requires-Dist: pytest (==7.1.3) ; extra == 'dev'
